foxylint/__init__.py
foxylint/imports.py
foxylint/loggingcase.py
foxylint/main.py
foxylint/noyml.py
foxylint-1.3.1.dist-info/METADATA
foxylint-1.3.1.dist-info/WHEEL
foxylint-1.3.1.dist-info/entry_points.txt
foxylint-1.3.1.dist-info/RECORD
