Metadata-Version: 2.1
Name: foxylint
Version: 1.3.1
Summary: 
License: MIT
Author: Yoav Kleinberger
Author-email: haarcuba@gmail.com
Requires-Python: >=3.11,<4.0
Classifier: License :: OSI Approved :: MIT License
Classifier: Programming Language :: Python :: 3
Classifier: Programming Language :: Python :: 3.11
Classifier: Programming Language :: Python :: 3.12
Classifier: Programming Language :: Python :: 3.13
Requires-Dist: click (>=8.1.7,<9.0.0)
